llama_index/embeddings/octoai/BUILD
llama_index/embeddings/octoai/__init__.py
llama_index/embeddings/octoai/base.py
llama_index/embeddings/octoai/utils.py
llama_index_embeddings_octoai-0.3.0.dist-info/METADATA
llama_index_embeddings_octoai-0.3.0.dist-info/WHEEL
llama_index_embeddings_octoai-0.3.0.dist-info/RECORD
