Metadata-Version: 2.1
Name: llama-index-embeddings-octoai
Version: 0.3.0
Summary: llama-index embeddings octoai integration
License: MIT
Author: Pedro Torruella
Author-email: 5025399+ptorru@users.noreply.github.com
Requires-Python: >=3.9,<4.0
Classifier: License :: OSI Approved :: MIT License
Classifier: Programming Language :: Python :: 3
Classifier: Programming Language :: Python :: 3.9
Classifier: Programming Language :: Python :: 3.10
Classifier: Programming Language :: Python :: 3.11
Classifier: Programming Language :: Python :: 3.12
Requires-Dist: llama-index-core (>=0.12.0,<0.13.0)
Requires-Dist: llama-index-embeddings-openai (>=0.3.0,<0.4.0)
